[{"line":1,"elements":[{"start_timestamp":"2022-03-30T03:29:30.290Z","line":22,"name":"Scenario7","description":"","id":"using-of-tags-in-cucumber;scenario7","type":"scenario","keyword":"Scenario","steps":[{"result":{"duration":6975000,"status":"passed"},"line":23,"name":"This is Scenario7","match":{"location":"com.stepDefinition.TagsDemo.this_is_scenario7()"},"keyword":"Given "}],"tags":[{"name":"@SmokeTest"},{"name":"@SanityTest"}]}],"name":"using of Tags in Cucumber","description":"","id":"using-of-tags-in-cucumber","keyword":"Feature","uri":"file:src/test/resources/FeatureFiles/Tags.feature","tags":[]}]